pynwb/__init__.py
pynwb/_due.py
pynwb/_version.py
pynwb/base.py
pynwb/behavior.py
pynwb/core.py
pynwb/device.py
pynwb/ecephys.py
pynwb/epoch.py
pynwb/file.py
pynwb/icephys.py
pynwb/image.py
pynwb/misc.py
pynwb/ogen.py
pynwb/ophys.py
pynwb/resources.py
pynwb/retinotopy.py
pynwb/spec.py
pynwb/validation.py
pynwb/validation_cli.py
pynwb/config/nwb_config.yaml
pynwb/config/nwb_subject_termset.yaml
pynwb/io/__init__.py
pynwb/io/base.py
pynwb/io/behavior.py
pynwb/io/core.py
pynwb/io/ecephys.py
pynwb/io/epoch.py
pynwb/io/file.py
pynwb/io/icephys.py
pynwb/io/image.py
pynwb/io/misc.py
pynwb/io/ogen.py
pynwb/io/ophys.py
pynwb/io/retinotopy.py
pynwb/io/utils.py
pynwb/legacy/__init__.py
pynwb/legacy/map.py
pynwb/legacy/io/__init__.py
pynwb/legacy/io/base.py
pynwb/legacy/io/behavior.py
pynwb/legacy/io/ecephys.py
pynwb/legacy/io/epoch.py
pynwb/legacy/io/file.py
pynwb/legacy/io/icephys.py
pynwb/legacy/io/image.py
pynwb/legacy/io/misc.py
pynwb/legacy/io/ogen.py
pynwb/legacy/io/ophys.py
pynwb/legacy/io/retinotopy.py
pynwb/nwb-schema/.codespellrc
pynwb/nwb-schema/Legal.txt
pynwb/nwb-schema/README.rst
pynwb/nwb-schema/license.txt
pynwb/nwb-schema/nwb.schema.json
pynwb/nwb-schema/requirements-doc.txt
pynwb/nwb-schema/core/nwb.base.yaml
pynwb/nwb-schema/core/nwb.behavior.yaml
pynwb/nwb-schema/core/nwb.device.yaml
pynwb/nwb-schema/core/nwb.ecephys.yaml
pynwb/nwb-schema/core/nwb.epoch.yaml
pynwb/nwb-schema/core/nwb.file.yaml
pynwb/nwb-schema/core/nwb.icephys.yaml
pynwb/nwb-schema/core/nwb.image.yaml
pynwb/nwb-schema/core/nwb.misc.yaml
pynwb/nwb-schema/core/nwb.namespace.yaml
pynwb/nwb-schema/core/nwb.ogen.yaml
pynwb/nwb-schema/core/nwb.ophys.yaml
pynwb/nwb-schema/core/nwb.retinotopy.yaml
pynwb/nwb-schema/docs/Readme.md
pynwb/nwb-schema/docs/format/Makefile
pynwb/nwb-schema/docs/format/Readme.md
pynwb/nwb-schema/docs/format/make.bat
pynwb/nwb-schema/docs/format/source/conf.py
pynwb/nwb-schema/docs/format/source/conf_doc_autogen.py
pynwb/nwb-schema/docs/format/source/credits.rst
pynwb-3.1.1.dist-info/METADATA
pynwb-3.1.1.dist-info/WHEEL
pynwb-3.1.1.dist-info/entry_points.txt
pynwb-3.1.1.dist-info/RECORD
