Metadata-Version: 2.4
Name: pynwb
Version: 3.1.1
Summary: Package for working with Neurodata stored in the NWB format.
Project-URL: Homepage, https://github.com/NeurodataWithoutBorders/pynwb
Project-URL: Bug Tracker, https://github.com/NeurodataWithoutBorders/pynwb/issues
Author-email: Andrew Tritt <ajtritt@lbl.gov>, Ryan Ly <rly@lbl.gov>, Oliver Ruebel <oruebel@lbl.gov>, Ben Dichter <ben.dichter@gmail.com>, Matthew Avaylon <mavaylon@lbl.gov>, Stephanie Prince <smprince@lbl.gov>
License: BSD-3-Clause
Classifier: Development Status :: 5 - Production/Stable
Classifier: Intended Audience :: Developers
Classifier: Intended Audience :: Science/Research
Classifier: License :: OSI Approved :: BSD License
Classifier: Operating System :: MacOS
Classifier: Operating System :: Microsoft :: Windows
Classifier: Operating System :: Unix
Classifier: Programming Language :: Python
Classifier: Programming Language :: Python :: 3.9
Classifier: Programming Language :: Python :: 3.10
Classifier: Programming Language :: Python :: 3.11
Classifier: Programming Language :: Python :: 3.12
Classifier: Programming Language :: Python :: 3.13
Classifier: Topic :: Scientific/Engineering :: Medical Science Apps.
Requires-Python: >=3.9
Requires-Dist: h5py>=3.2.0
Requires-Dist: hdmf<5,>=4.1.0
Requires-Dist: numpy>=1.24.0
Requires-Dist: pandas>=1.2.0
Requires-Dist: platformdirs>=4.1.0
Requires-Dist: python-dateutil>=2.8.2
